meand23/__init__.py
meand23/creds.py
meand23/meand23.py
meand23-0.0.2.dist-info/LICENSE
meand23-0.0.2.dist-info/METADATA
meand23-0.0.2.dist-info/WHEEL
meand23-0.0.2.dist-info/top_level.txt
meand23-0.0.2.dist-info/RECORD
