Metadata-Version: 2.1
Name: meand23
Version: 0.0.2
Summary: 23andme API
Home-page: https://github.com/andyh2/meand23
Author: andyh2
Author-email: andyh2@mac.com
License: UNKNOWN
Platform: UNKNOWN
Classifier: Programming Language :: Python :: 3
Classifier: License :: OSI Approved :: MIT License
Classifier: Operating System :: OS Independent
Requires-Python: >=3.6
License-File: LICENSE
Requires-Dist: requests
